cobra/__init__.py
cobra/usar_loader.py
cobra/cli/__init__.py
cobra/cli/cli.py
cobra/cli/cobrahub_client.py
cobra/cli/i18n.py
cobra/cli/plugin.py
cobra/cli/plugin_interface.py
cobra/cli/plugin_loader.py
cobra/cli/plugin_registry.py
cobra/cli/commands/__init__.py
cobra/cli/commands/agix_cmd.py
cobra/cli/commands/base.py
cobra/cli/commands/bench_cmd.py
cobra/cli/commands/bench_transpilers_cmd.py
cobra/cli/commands/benchmarks2_cmd.py
cobra/cli/commands/benchmarks_cmd.py
cobra/cli/commands/benchthreads_cmd.py
cobra/cli/commands/cache_cmd.py
cobra/cli/commands/compile_cmd.py
cobra/cli/commands/container_cmd.py
cobra/cli/commands/crear_cmd.py
cobra/cli/commands/dependencias_cmd.py
cobra/cli/commands/docs_cmd.py
cobra/cli/commands/empaquetar_cmd.py
cobra/cli/commands/execute_cmd.py
cobra/cli/commands/flet_cmd.py
cobra/cli/commands/init_cmd.py
cobra/cli/commands/interactive_cmd.py
cobra/cli/commands/jupyter_cmd.py
cobra/cli/commands/modules_cmd.py
cobra/cli/commands/package_cmd.py
cobra/cli/commands/plugins_cmd.py
cobra/cli/commands/profile_cmd.py
cobra/cli/commands/qualia_cmd.py
cobra/cli/commands/transpilar_inverso_cmd.py
cobra/cli/commands/verify_cmd.py
cobra/cli/utils/__init__.py
cobra/cli/utils/messages.py
cobra/cli/utils/semver.py
cobra/lexico/__init__.py
cobra/lexico/lexer.py
cobra/macro/__init__.py
cobra/parser/__init__.py
cobra/parser/lark_parser.py
cobra/parser/parser.py
cobra/semantico/__init__.py
cobra/semantico/analizador.py
cobra/semantico/cobra_mod_schema.yaml
cobra/semantico/mod_validator.py
cobra/semantico/tabla.py
cobra/transpilers/__init__.py
cobra/transpilers/base.py
cobra/transpilers/import_helper.py
cobra/transpilers/module_map.py
cobra/transpilers/semantica.py
cobra/transpilers/reverse/__init__.py
cobra/transpilers/reverse/base.py
cobra/transpilers/reverse/from_asm.py
cobra/transpilers/reverse/from_c.py
cobra/transpilers/reverse/from_cobol.py
cobra/transpilers/reverse/from_cpp.py
cobra/transpilers/reverse/from_fortran.py
cobra_lenguaje-10.0.5.dist-info/licenses/LICENSE
cobra_lenguaje-10.0.5.dist-info/METADATA
cobra_lenguaje-10.0.5.dist-info/WHEEL
cobra_lenguaje-10.0.5.dist-info/entry_points.txt
cobra_lenguaje-10.0.5.dist-info/top_level.txt
cobra_lenguaje-10.0.5.dist-info/RECORD
