Metadata-Version: 2.4
Name: cobra-lenguaje
Version: 10.0.5
Summary: Un lenguaje de programación en español para simulaciones y más.
Author-email: Adolfo González Hernández <adolfogonzal@gmail.com>
License: MIT
Project-URL: Documentation, https://github.com/Alphonsus411/pCobra#readme
Project-URL: Source, https://github.com/Alphonsus411/pCobra
Keywords: cobra,lenguaje,cli
Requires-Python: >=3.8
License-File: LICENSE
Requires-Dist: numpy>=1.22.0
Requires-Dist: scipy>=1.7.0
Requires-Dist: matplotlib>=3.5.0
Requires-Dist: pandas>=1.3.0
Requires-Dist: tensorflow>=2.6.0
Requires-Dist: dask>=2021.09.0
Requires-Dist: DEAP>=1.3.1
Requires-Dist: agix==1.0.0
Requires-Dist: holobit-sdk==1.0.8
Requires-Dist: smooth-criminal==0.4.0
Requires-Dist: tomli>=2.0
Requires-Dist: PyYAML>=6.0
Requires-Dist: jsonschema>=4.24.0
Requires-Dist: python-dotenv
Requires-Dist: pexpect
Requires-Dist: requests
Requires-Dist: flet
Requires-Dist: packaging
Requires-Dist: pybind11>=2.13.6
Requires-Dist: RestrictedPython>=8.0
Provides-Extra: mutation
Requires-Dist: mutpy>=0.6.1; extra == "mutation"
Provides-Extra: notebooks
Requires-Dist: papermill>=2.6.0; extra == "notebooks"
Requires-Dist: nbconvert>=7.16.6; extra == "notebooks"
Requires-Dist: ipykernel>=6.29.5; extra == "notebooks"
Provides-Extra: dev
Requires-Dist: python-dotenv; extra == "dev"
Requires-Dist: python-lsp-server; extra == "dev"
Requires-Dist: hypothesis; extra == "dev"
Requires-Dist: ipykernel>=6.29.5; extra == "dev"
Requires-Dist: tree-sitter-languages>=1.10.2; extra == "dev"
Requires-Dist: pytest; extra == "dev"
Requires-Dist: pytest-cov; extra == "dev"
Requires-Dist: pytest-timeout; extra == "dev"
Dynamic: license-file
